analyze.py
image_palette_extractor-0.4.0.dist-info/METADATA
image_palette_extractor-0.4.0.dist-info/WHEEL
image_palette_extractor-0.4.0.dist-info/entry_points.txt
image_palette_extractor-0.4.0.dist-info/top_level.txt
image_palette_extractor-0.4.0.dist-info/RECORD
