Metadata-Version: 2.4
Name: image-palette-extractor
Version: 0.4.0
Summary: Extract color palettes from images for web design. Produces LLM-consumable prose with color roles, WCAG contrast pairs, and harmonic relationships.
Author: Simon Sorkin
License: MIT
Project-URL: Repository, https://github.com/Capacap/palette-extractor
Requires-Python: >=3.10
Requires-Dist: pillow>=10.0.0
Requires-Dist: numpy>=1.24.0
Requires-Dist: scipy>=1.11.0
